<annotation>
	<folder>HDPE</folder>
	<filename>PET &amp; HDPE - 1.jpg</filename>
	<path>/home/henbx/Pictures/dataset/HDPE/PET &amp; HDPE - 1.jpg</path>
	<source>
		<database>Unknown</database>
	</source>
	<size>
		<width>4160</width>
		<height>3120</height>
		<depth>3</depth>
	</size>
	<segmented>0</segmented>
	<object>
		<name>HDPE</name>
		<pose>Unspecified</pose>
		<truncated>0</truncated>
		<difficult>0</difficult>
		<bndbox>
			<xmin>1410</xmin>
			<ymin>1264</ymin>
			<xmax>2565</xmax>
			<ymax>1935</ymax>
		</bndbox>
	</object>
	<object>
		<name>PET</name>
		<pose>Unspecified</pose>
		<truncated>0</truncated>
		<difficult>0</difficult>
		<bndbox>
			<xmin>2545</xmin>
			<ymin>1267</ymin>
			<xmax>3168</xmax>
			<ymax>1899</ymax>
		</bndbox>
	</object>
</annotation>
